[
  {
    "tweet": "@adamcjonas Very happy someone finally built this. \n\nHave you considered threading the replies/summaries on a single page and nest original posts to avoid navigation back n forth?",
    "name": "Alex B",
    "username": "bergealex4",
    "profileImage": "https://pbs.twimg.com/profile_images/1780400690226982912/ZDqgFnIk_normal.jpg",
    "url": "https://x.com/bergealex4/status/1713969652991168655"
  },
  {
    "tweet": "@adamcjonas 👏🏼🎉🕺",
    "name": "satsie",
    "username": "satsie",
    "profileImage": "https://pbs.twimg.com/profile_images/1490885395390861317/MOzYmFOn_normal.jpg",
    "url": "https://x.com/satsie/status/1714017569726706162"
  },
  {
    "tweet": "This is amazing🎉 https://t.co/yG9cqCKNKQ",
    "name": "aljaz",
    "username": "aaaljaz",
    "profileImage": "https://pbs.twimg.com/profile_images/1590341548515926017/uCqa9DKX_normal.jpg",
    "url": "https://x.com/aaaljaz/status/1713969266448347235"
  },
  {
    "tweet": "This is an amazing project and will help so many more people to participate in the Bitcoin thought process.\n\n🕊️🙏🧡 https://t.co/20JTzruYLM",
    "name": "calle",
    "username": "callebtc",
    "profileImage": "https://pbs.twimg.com/profile_images/1719881482070540288/bZIoBxFq_normal.jpg",
    "url": "https://x.com/callebtc/status/1713964494487994658"
  },
  {
    "tweet": "@adamcjonas Really cool! Nice work",
    "name": "₿ Steve Lee | #TeamSlowAndSteady",
    "username": "moneyball",
    "profileImage": "https://pbs.twimg.com/profile_images/1723113861673598976/-0CYhHzn_normal.jpg",
    "url": "https://x.com/moneyball/status/1714089589605077025"
  },
  {
    "tweet": "@adamcjonas Wow! Fantastic work!",
    "name": "calle",
    "username": "callebtc",
    "profileImage": "https://pbs.twimg.com/profile_images/1719881482070540288/bZIoBxFq_normal.jpg",
    "url": "https://x.com/callebtc/status/1713963375254777963"
  },
  {
    "tweet": "This is awesome, it's tough trying to stay up to date on all the cool new ideas flowing throw the developer mailing lists. These summaries make following a long a little bit easier.\n\nSide note: show this to anyone who thinks bitcoin isn't innovating 🤪 https://t.co/TujnRCiYXZ",
    "name": "Alyssa Ferris",
    "username": "mehmehturtle",
    "profileImage": "https://pbs.twimg.com/profile_images/1814510679950266368/6cQHrlYw_normal.jpg",
    "url": "https://x.com/mehmehturtle/status/1714150769321030030"
  },
  {
    "tweet": "This is amazing. Well needed. https://t.co/Ok4jHw2MnQ",
    "name": "Timechain",
    "username": "timechain_",
    "profileImage": "https://pbs.twimg.com/profile_images/1455391902396735489/kxxWoSOe_normal.jpg",
    "url": "https://x.com/timechain_/status/1713990636024606790"
  },
  {
    "tweet": "@adamcjonas Great idea 👏👏",
    "name": "Botanix Labs 🕷",
    "username": "BotanixLabs",
    "profileImage": "https://pbs.twimg.com/profile_images/1876426098508189696/xcmLLhZB_normal.jpg",
    "url": "https://x.com/BotanixLabs/status/1714264279388426689"
  },
  {
    "tweet": "TLDR is a platform summarizing technical discussions from bitcoin-dev and lightning-dev mailing lists; simplifying them for readers and thus making high-signal discussions about #bitcoin and lightning easier to navigate 🧭 \n\nCheck it out 👇 https://t.co/lCpjQuZPQc @adamcjonas",
    "name": "Simply Bitcoin",
    "username": "SimplyBitcoinTV",
    "profileImage": "https://pbs.twimg.com/profile_images/1832112477003243521/0Oflh1fM_normal.jpg",
    "url": "https://x.com/SimplyBitcoinTV/status/1714219210425971193"
  },
  {
    "tweet": "Incredibly proud to 🚢 this one!\n\nWith TDLR, high signal discussions about bitcoin and lightning are easier to navigate. \n\nUse it and let us know what you think! \n\nhttps://t.co/Mw68DVehhL https://t.co/hY8l2pAowZ",
    "name": "Art Assoiants",
    "username": "aassoiants",
    "profileImage": "https://pbs.twimg.com/profile_images/1878875919089377280/iLYzjbyE_normal.jpg",
    "url": "https://x.com/aassoiants/status/1713997638129856611"
  }
]